azure/mgmt/dashboard/__init__.py
azure/mgmt/dashboard/_client.py
azure/mgmt/dashboard/_configuration.py
azure/mgmt/dashboard/_patch.py
azure/mgmt/dashboard/_version.py
azure/mgmt/dashboard/py.typed
azure/mgmt/dashboard/_utils/__init__.py
azure/mgmt/dashboard/_utils/model_base.py
azure/mgmt/dashboard/_utils/serialization.py
azure/mgmt/dashboard/aio/__init__.py
azure/mgmt/dashboard/aio/_client.py
azure/mgmt/dashboard/aio/_configuration.py
azure/mgmt/dashboard/aio/_patch.py
azure/mgmt/dashboard/aio/operations/__init__.py
azure/mgmt/dashboard/aio/operations/_operations.py
azure/mgmt/dashboard/aio/operations/_patch.py
azure/mgmt/dashboard/models/__init__.py
azure/mgmt/dashboard/models/_enums.py
azure/mgmt/dashboard/models/_models.py
azure/mgmt/dashboard/models/_patch.py
azure/mgmt/dashboard/operations/__init__.py
azure/mgmt/dashboard/operations/_operations.py
azure/mgmt/dashboard/operations/_patch.py
azure_mgmt_dashboard-2.0.0.dist-info/licenses/LICENSE
azure_mgmt_dashboard-2.0.0.dist-info/METADATA
azure_mgmt_dashboard-2.0.0.dist-info/WHEEL
azure_mgmt_dashboard-2.0.0.dist-info/top_level.txt
azure_mgmt_dashboard-2.0.0.dist-info/RECORD
